Metadata-Version: 1.1
Name: sxtools
Version: 1.0.1
Summary: Useful Functions Set: Remove Accents, Pluralize, Deep Encode and etc..
Home-page: https://github.com/sxslex/sxtools
Author: Alexandre Villela (SleX)
Author-email: sx.slex@gmail.com
License: UNKNOWN
Download-URL: https://github.com/sxslex/sxtools/archive/v1.0.1.tar.gz
Keywords: remove,accents,pluralize,join_plus,deep,encode,decode,capitalize
Platform: UNKNOWN
Classifier: License :: OSI Approved :: GNU General Public License (GPL)
Classifier: Natural Language :: English
Classifier: Operating System :: OS Independent
Classifier: Programming Language :: Python :: 2.6
Classifier: Programming Language :: Python :: 2.7
Classifier: Programming Language :: Python :: 3.3
Classifier: Programming Language :: Python :: 3.4
Classifier: Programming Language :: Python :: 3.5
Classifier: Programming Language :: Python :: 3.6
Classifier: Topic :: Software Development :: Libraries :: Python Modules
